{
    "roc": [
        {
            "fpr": 0.0,
            "tpr": 0.0,
            "threshold": 1.9459882677708764
        },
        {
            "fpr": 0.0,
            "tpr": 0.009708737864077669,
            "threshold": 0.9459882677708764
        },
        {
            "fpr": 0.0,
            "tpr": 0.02912621359223301,
            "threshold": 0.9455527355939255
        },
        {
            "fpr": 0.0,
            "tpr": 0.04854368932038835,
            "threshold": 0.9255527355939256
        },
        {
            "fpr": 0.0,
            "tpr": 0.06796116504854369,
            "threshold": 0.9220067862893948
        },
        {
            "fpr": 0.0,
            "tpr": 0.0970873786407767,
            "threshold": 0.9177734204793028
        },
        {
            "fpr": 0.0,
            "tpr": 0.10679611650485436,
            "threshold": 0.9176475972540047
        },
        {
            "fpr": 0.0,
            "tpr": 0.1262135922330097,
            "threshold": 0.9127734204793028
        },
        {
            "fpr": 0.0,
            "tpr": 0.14563106796116504,
            "threshold": 0.8875613897596656
        },
        {
            "fpr": 0.0,
            "tpr": 0.17475728155339806,
            "threshold": 0.8727812002812003
        },
        {
            "fpr": 0.0,
            "tpr": 0.1941747572815534,
            "threshold": 0.8586722600238342
        },
        {
            "fpr": 0.0,
            "tpr": 0.22330097087378642,
            "threshold": 0.8231754658385093
        },
        {
            "fpr": 0.006060606060606061,
            "tpr": 0.23300970873786409,
            "threshold": 0.810783784486933
        },
        {
            "fpr": 0.006060606060606061,
            "tpr": 0.2524271844660194,
            "threshold": 0.8028144224196856
        },
        {
            "fpr": 0.006060606060606061,
            "tpr": 0.27184466019417475,
            "threshold": 0.7923971861471861
        },
        {
            "fpr": 0.012121212121212121,
            "tpr": 0.30097087378640774,
            "threshold": 0.7913290598290598
        },
        {
            "fpr": 0.01818181818181818,
            "tpr": 0.3106796116504854,
            "threshold": 0.7809886257851466
        },
        {
            "fpr": 0.01818181818181818,
            "tpr": 0.32038834951456313,
            "threshold": 0.7788941694376478
        },
        {
            "fpr": 0.01818181818181818,
            "tpr": 0.33980582524271846,
            "threshold": 0.7764052795031056
        },
        {
            "fpr": 0.01818181818181818,
            "tpr": 0.36893203883495146,
            "threshold": 0.7731966540748005
        },
        {
            "fpr": 0.024242424242424242,
            "tpr": 0.36893203883495146,
            "threshold": 0.7730270801323433
        },
        {
            "fpr": 0.024242424242424242,
            "tpr": 0.4077669902912621,
            "threshold": 0.7462533316674996
        },
        {
            "fpr": 0.030303030303030304,
            "tpr": 0.4077669902912621,
            "threshold": 0.7440877721312504
        },
        {
            "fpr": 0.030303030303030304,
            "tpr": 0.4174757281553398,
            "threshold": 0.7403183229813665
        },
        {
            "fpr": 0.03636363636363636,
            "tpr": 0.42718446601941745,
            "threshold": 0.7334396239831024
        },
        {
            "fpr": 0.03636363636363636,
            "tpr": 0.5145631067961165,
            "threshold": 0.6928564491064492
        },
        {
            "fpr": 0.04242424242424243,
            "tpr": 0.5242718446601942,
            "threshold": 0.6910841865171238
        },
        {
            "fpr": 0.048484848484848485,
            "tpr": 0.5242718446601942,
            "threshold": 0.6878418949471581
        },
        {
            "fpr": 0.048484848484848485,
            "tpr": 0.5436893203883495,
            "threshold": 0.6843646818867407
        },
        {
            "fpr": 0.048484848484848485,
            "tpr": 0.5631067961165048,
            "threshold": 0.6700292886620118
        },
        {
            "fpr": 0.05454545454545454,
            "tpr": 0.5631067961165048,
            "threshold": 0.6575591489969301
        },
        {
            "fpr": 0.05454545454545454,
            "tpr": 0.5825242718446602,
            "threshold": 0.6347760589402269
        },
        {
            "fpr": 0.05454545454545454,
            "tpr": 0.6407766990291263,
            "threshold": 0.6339373314593904
        },
        {
            "fpr": 0.05454545454545454,
            "tpr": 0.6699029126213593,
            "threshold": 0.5944114060811854
        },
        {
            "fpr": 0.06060606060606061,
            "tpr": 0.6699029126213593,
            "threshold": 0.5866614168101583
        },
        {
            "fpr": 0.08484848484848485,
            "tpr": 0.6893203883495146,
            "threshold": 0.581292519850457
        },
        {
            "fpr": 0.09090909090909091,
            "tpr": 0.6893203883495146,
            "threshold": 0.5762121212121212
        },
        {
            "fpr": 0.09696969696969697,
            "tpr": 0.7087378640776699,
            "threshold": 0.5692314491064492
        },
        {
            "fpr": 0.10303030303030303,
            "tpr": 0.7184466019417476,
            "threshold": 0.5639839073894801
        },
        {
            "fpr": 0.10303030303030303,
            "tpr": 0.7378640776699029,
            "threshold": 0.5417148553201184
        },
        {
            "fpr": 0.12121212121212122,
            "tpr": 0.7378640776699029,
            "threshold": 0.4943194806347707
        },
        {
            "fpr": 0.13333333333333333,
            "tpr": 0.7378640776699029,
            "threshold": 0.4882935912995882
        },
        {
            "fpr": 0.14545454545454545,
            "tpr": 0.7378640776699029,
            "threshold": 0.48398390738948016
        },
        {
            "fpr": 0.14545454545454545,
            "tpr": 0.7475728155339806,
            "threshold": 0.47944444444444445
        },
        {
            "fpr": 0.15151515151515152,
            "tpr": 0.7475728155339806,
            "threshold": 0.4720553030353393
        },
        {
            "fpr": 0.15757575757575756,
            "tpr": 0.7572815533980582,
            "threshold": 0.4706026272577997
        },
        {
            "fpr": 0.1696969696969697,
            "tpr": 0.7669902912621359,
            "threshold": 0.4591770872805355
        },
        {
            "fpr": 0.18787878787878787,
            "tpr": 0.7669902912621359,
            "threshold": 0.45829359129958824
        },
        {
            "fpr": 0.18787878787878787,
            "tpr": 0.7766990291262136,
            "threshold": 0.4571241830065359
        },
        {
            "fpr": 0.19393939393939394,
            "tpr": 0.7961165048543689,
            "threshold": 0.45335831954783573
        },
        {
            "fpr": 0.2,
            "tpr": 0.7961165048543689,
            "threshold": 0.4186154746526264
        },
        {
            "fpr": 0.2,
            "tpr": 0.8155339805825242,
            "threshold": 0.41383228291316526
        },
        {
            "fpr": 0.20606060606060606,
            "tpr": 0.8155339805825242,
            "threshold": 0.4103727483816494
        },
        {
            "fpr": 0.20606060606060606,
            "tpr": 0.8252427184466019,
            "threshold": 0.40912601997320663
        },
        {
            "fpr": 0.22424242424242424,
            "tpr": 0.8252427184466019,
            "threshold": 0.40798661109005935
        },
        {
            "fpr": 0.24848484848484848,
            "tpr": 0.8252427184466019,
            "threshold": 0.3913199444233927
        },
        {
            "fpr": 0.2545454545454545,
            "tpr": 0.8349514563106796,
            "threshold": 0.38913587848932674
        },
        {
            "fpr": 0.2545454545454545,
            "tpr": 0.8446601941747572,
            "threshold": 0.3889327369369314
        },
        {
            "fpr": 0.2606060606060606,
            "tpr": 0.8446601941747572,
            "threshold": 0.3873676653736623
        },
        {
            "fpr": 0.2727272727272727,
            "tpr": 0.8446601941747572,
            "threshold": 0.3740994036035981
        },
        {
            "fpr": 0.2727272727272727,
            "tpr": 0.8543689320388349,
            "threshold": 0.3729966524703367
        },
        {
            "fpr": 0.2787878787878788,
            "tpr": 0.8640776699029126,
            "threshold": 0.3580316994833124
        },
        {
            "fpr": 0.2787878787878788,
            "tpr": 0.883495145631068,
            "threshold": 0.35201956540191837
        },
        {
            "fpr": 0.2909090909090909,
            "tpr": 0.883495145631068,
            "threshold": 0.3449220183504744
        },
        {
            "fpr": 0.2909090909090909,
            "tpr": 0.8932038834951457,
            "threshold": 0.3387035378414689
        },
        {
            "fpr": 0.2909090909090909,
            "tpr": 0.912621359223301,
            "threshold": 0.33465327775672604
        },
        {
            "fpr": 0.3090909090909091,
            "tpr": 0.912621359223301,
            "threshold": 0.32102652249711083
        },
        {
            "fpr": 0.3151515151515151,
            "tpr": 0.9223300970873787,
            "threshold": 0.31420544367912795
        },
        {
            "fpr": 0.3393939393939394,
            "tpr": 0.9223300970873787,
            "threshold": 0.29093446783101956
        },
        {
            "fpr": 0.34545454545454546,
            "tpr": 0.9320388349514563,
            "threshold": 0.2873676653736623
        },
        {
            "fpr": 0.3515151515151515,
            "tpr": 0.9320388349514563,
            "threshold": 0.28332029977191275
        },
        {
            "fpr": 0.3696969696969697,
            "tpr": 0.9320388349514563,
            "threshold": 0.2816487535453053
        },
        {
            "fpr": 0.37575757575757573,
            "tpr": 0.9320388349514563,
            "threshold": 0.2675763525297783
        },
        {
            "fpr": 0.37575757575757573,
            "tpr": 0.9514563106796117,
            "threshold": 0.2595719919679875
        },
        {
            "fpr": 0.4121212121212121,
            "tpr": 0.9514563106796117,
            "threshold": 0.22184188799706042
        },
        {
            "fpr": 0.4484848484848485,
            "tpr": 0.9514563106796117,
            "threshold": 0.2146634411340294
        },
        {
            "fpr": 0.46060606060606063,
            "tpr": 0.9514563106796117,
            "threshold": 0.2095506792058516
        },
        {
            "fpr": 0.47878787878787876,
            "tpr": 0.9514563106796117,
            "threshold": 0.20766573295985064
        },
        {
            "fpr": 0.4909090909090909,
            "tpr": 0.9514563106796117,
            "threshold": 0.2048084225715805
        },
        {
            "fpr": 0.503030303030303,
            "tpr": 0.9514563106796117,
            "threshold": 0.1934219048269435
        },
        {
            "fpr": 0.5151515151515151,
            "tpr": 0.9514563106796117,
            "threshold": 0.1876046176046176
        },
        {
            "fpr": 0.5272727272727272,
            "tpr": 0.9611650485436893,
            "threshold": 0.18444444444444444
        },
        {
            "fpr": 0.5454545454545454,
            "tpr": 0.9611650485436893,
            "threshold": 0.17332089006002047
        },
        {
            "fpr": 0.5636363636363636,
            "tpr": 0.970873786407767,
            "threshold": 0.16669552669552667
        },
        {
            "fpr": 0.5696969696969697,
            "tpr": 0.970873786407767,
            "threshold": 0.15489606641249984
        },
        {
            "fpr": 0.5818181818181818,
            "tpr": 0.970873786407767,
            "threshold": 0.15277777777777776
        },
        {
            "fpr": 0.6242424242424243,
            "tpr": 0.970873786407767,
            "threshold": 0.14942190482694348
        },
        {
            "fpr": 0.6303030303030303,
            "tpr": 0.970873786407767,
            "threshold": 0.13671424823068165
        },
        {
            "fpr": 0.6424242424242425,
            "tpr": 0.970873786407767,
            "threshold": 0.13111111111111112
        },
        {
            "fpr": 0.6484848484848484,
            "tpr": 0.970873786407767,
            "threshold": 0.1282874525022233
        },
        {
            "fpr": 0.6606060606060606,
            "tpr": 0.970873786407767,
            "threshold": 0.12755489679402723
        },
        {
            "fpr": 0.6606060606060606,
            "tpr": 0.9805825242718447,
            "threshold": 0.1270306447938027
        },
        {
            "fpr": 0.6727272727272727,
            "tpr": 0.9805825242718447,
            "threshold": 0.12312588319070372
        },
        {
            "fpr": 0.696969696969697,
            "tpr": 0.9805825242718447,
            "threshold": 0.12292808069123859
        },
        {
            "fpr": 0.7272727272727273,
            "tpr": 0.9805825242718447,
            "threshold": 0.09886614281775571
        },
        {
            "fpr": 0.7575757575757576,
            "tpr": 0.9805825242718447,
            "threshold": 0.09569404043668751
        },
        {
            "fpr": 0.7757575757575758,
            "tpr": 0.9805825242718447,
            "threshold": 0.08477711901624944
        },
        {
            "fpr": 0.7818181818181819,
            "tpr": 0.9805825242718447,
            "threshold": 0.08381603761399158
        },
        {
            "fpr": 0.793939393939394,
            "tpr": 0.9902912621359223,
            "threshold": 0.07127272727272727
        },
        {
            "fpr": 0.806060606060606,
            "tpr": 0.9902912621359223,
            "threshold": 0.05701811536627999
        },
        {
            "fpr": 0.8181818181818182,
            "tpr": 0.9902912621359223,
            "threshold": 0.05273023766011144
        },
        {
            "fpr": 0.8242424242424242,
            "tpr": 0.9902912621359223,
            "threshold": 0.04963343108504399
        },
        {
            "fpr": 0.8606060606060606,
            "tpr": 1.0,
            "threshold": 0.04735840897049766
        },
        {
            "fpr": 0.9090909090909091,
            "tpr": 1.0,
            "threshold": 0.04691622245330685
        },
        {
            "fpr": 0.9212121212121213,
            "tpr": 1.0,
            "threshold": 0.044
        },
        {
            "fpr": 0.9393939393939394,
            "tpr": 1.0,
            "threshold": 0.039352045803658704
        },
        {
            "fpr": 0.9454545454545454,
            "tpr": 1.0,
            "threshold": 0.02463343108504399
        },
        {
            "fpr": 0.9696969696969697,
            "tpr": 1.0,
            "threshold": 0.021603128054740958
        },
        {
            "fpr": 1.0,
            "tpr": 1.0,
            "threshold": 0.0
        }
    ]
}
